{
  "eta_ceiling": 2.0,
  "tolerance": 0.1,
  "observed": [
    {
      "drift": 0.005,
      "eta_max": 1.0625,
      "S": 1.0264508716866632
    },
    {
      "drift": 0.01,
      "eta_max": 0.0,
      "S": 0.9970285056825469
    },
    {
      "drift": 0.02,
      "eta_max": 1.0625,
      "S": 1.2638899155987098
    },
    {
      "drift": 0.04,
      "eta_max": 0.0,
      "S": 0.9317635041412087
    },
    {
      "drift": 0.06,
      "eta_max": 0.0,
      "S": 0.8197082167050688
    },
    {
      "drift": 0.08,
      "eta_max": 0.0,
      "S": 0.7202320678846752
    },
    {
      "drift": 0.12,
      "eta_max": 0.0,
      "S": 0.11655427537680642
    }
  ],
  "censored": []
}